spiderling/__init__.py
spiderling/dispatcher.py
spiderling/listener.py
spiderling/logger.py
spiderling/sistema.py
spiderling-1.0.2.dist-info/METADATA
spiderling-1.0.2.dist-info/WHEEL
spiderling-1.0.2.dist-info/top_level.txt
spiderling-1.0.2.dist-info/RECORD
